envdesign_model/__init__.py
envdesign_model/envdesign_model_main.py
envdesign_model/utils.py
envdesign_model/graph_algorithms/__init__.py
envdesign_model/graph_algorithms/build_clique.py
envdesign_model/graph_algorithms/graph_algorithms.py
envdesign_model/io_validation/__init__.py
envdesign_model/io_validation/input_validation.py
envdesign_model/io_validation/io_validation_utils.py
envdesign_model/io_validation/output_validation.py
envdesign_model/optimization/__init__.py
envdesign_model/optimization/optimization_utils.py
envdesign_model/optimization/algorithms/__init__.py
envdesign_model/optimization/algorithms/expand_clique_cover_sa.py
envdesign_model/optimization/objective_functions/__init__.py
envdesign_model/optimization/objective_functions/mean_squared_error.py
envdesign_model/optimization/optimization_strategies/__init__.py
envdesign_model/optimization/optimization_strategies/optimization_params.py
envdesign_model/optimization/optimization_strategies/optimization_strategy.py
envdesign_model/optimization/optimization_strategies/optimization_strategy1.py
envdesign_model/optimization/optimization_strategies/optimization_strategy_utils.py
envdesign_model/output_postprocessing/__init__.py
envdesign_model/output_postprocessing/output_postprocessing.py
tests/graph_algorithms/__init__.py
tests/graph_algorithms/test_build_clique.py
tests/graph_algorithms/test_graph_algorithms.py
tests/io_validation/__init__.py
tests/io_validation/test_input_validation.py
tests/io_validation/test_io_validation_utils.py
tests/io_validation/test_output_validation.py
tests/optimization/__init__.py
tests/optimization/algorithms/__init__.py
tests/optimization/algorithms/test_expand_clique_cover_sa.py
tests/optimization/objective_functions/__init__.py
tests/optimization/objective_functions/test_mean_squared_error.py
tests/optimization/optimization_strategies/__init__.py
tests/optimization/optimization_strategies/test_optimization_params.py
envdesign_model-0.0.1.dist-info/LICENSE
envdesign_model-0.0.1.dist-info/METADATA
envdesign_model-0.0.1.dist-info/WHEEL
envdesign_model-0.0.1.dist-info/top_level.txt
envdesign_model-0.0.1.dist-info/RECORD
