Metadata-Version: 2.1
Name: envdesign-model
Version: 0.0.1
Summary: A domain-agnostic model that uses graph theory and optimization algorithms to design testing environments.
Author: Akshay Sathiya, Rohit Pandey
Author-email: akshay.sathiya@gmail.com, rohitpandey576@gmail.com
Requires-Python: >=2.7, !=3.0.*, !=3.1.*, !=3.2.*, !=3.3.*, <4
License-File: LICENSE
Requires-Dist: numpy
Requires-Dist: pandas
Requires-Dist: graphing
Requires-Dist: optimizn
Provides-Extra: dev
Provides-Extra: test
Requires-Dist: pytest ; extra == 'test'
